splurge_typer/__init__.py
splurge_typer/data_type.py
splurge_typer/duck_typing.py
splurge_typer/exceptions.py
splurge_typer/string.py
splurge_typer/type_inference.py
splurge_typer-2025.1.0.dist-info/licenses/LICENSE
splurge_typer-2025.1.0.dist-info/METADATA
splurge_typer-2025.1.0.dist-info/WHEEL
splurge_typer-2025.1.0.dist-info/top_level.txt
splurge_typer-2025.1.0.dist-info/RECORD
