Metadata-Version: 2.4
Name: splurge-typer
Version: 2025.1.0
Summary: Type Inference and Conversion Library for Python
Author: Jim Schilling
License-Expression: MIT
Project-URL: Homepage, http://github.com/jim-schilling/splurge-typer
Project-URL: Repository, http://github.com/jim-schilling/splurge-typer
Project-URL: Issues, http://github.com/jim-schilling/splurge-typer/issues
Project-URL: Changelog, http://github.com/jim-schilling/splurge-typer/blob/main/CHANGELOG.md
Keywords: type-inference,data-conversion,python,typing,data-processing
Classifier: Development Status :: 4 - Beta
Classifier: Intended Audience :: Developers
Classifier: Operating System :: OS Independent
Classifier: Programming Language :: Python :: 3
Classifier: Programming Language :: Python :: 3.10
Classifier: Programming Language :: Python :: 3.11
Classifier: Programming Language :: Python :: 3.12
Classifier: Programming Language :: Python :: 3.13
Classifier: Topic :: Software Development :: Libraries :: Python Modules
Classifier: Topic :: Utilities
Requires-Python: >=3.10
License-File: LICENSE
Provides-Extra: dev
Requires-Dist: pytest>=7.3; extra == "dev"
Requires-Dist: pytest-cov>=4.0; extra == "dev"
Requires-Dist: pytest-xdist>=3.0; extra == "dev"
Requires-Dist: hypothesis>=6.0; extra == "dev"
Requires-Dist: mypy>=1.18.2; extra == "dev"
Requires-Dist: ruff>=0.12.12; extra == "dev"
Requires-Dist: pre-commit>=3.4; extra == "dev"
Dynamic: license-file
